proxy_cheap/__init__.py
proxy_cheap/cheap.py
proxy_cheap-0.0.7.dist-info/METADATA
proxy_cheap-0.0.7.dist-info/WHEEL
proxy_cheap-0.0.7.dist-info/licenses/LICENSE
proxy_cheap-0.0.7.dist-info/RECORD
