Metadata-Version: 2.1
Name: proxy_cheap
Version: 0.0.7
Summary: proxy-cheap API python implementatione
Project-URL: Homepage, https://github.com/lr2bmail/proxy_cheap
Project-URL: Bug Tracker, https://github.com/lr2bmail/proxy_cheap/issues
Author-email: lr2bmail <lr2b.com@gmail.com>
License-File: LICENSE
Classifier: License :: OSI Approved :: MIT License
Classifier: Operating System :: OS Independent
Classifier: Programming Language :: Python :: 2
Classifier: Programming Language :: Python :: 3
Requires-Python: >=2.7
